pyslowloris/__init__.py
pyslowloris/__main__.py
pyslowloris/attack.py
pyslowloris/connection.py
pyslowloris/exceptions.py
pyslowloris/logger.py
pyslowloris/uri_info.py
pyslowloris/utils.py
pyslowloris-2.0.3.dist-info/LICENSE
pyslowloris-2.0.3.dist-info/METADATA
pyslowloris-2.0.3.dist-info/WHEEL
pyslowloris-2.0.3.dist-info/entry_points.txt
pyslowloris-2.0.3.dist-info/RECORD
